quicksave/__init__.py
quicksave/__main__.py
quicksave/qs_database.py
quicksave/utils.py
quicksave/commands/__init__.py
quicksave/commands/command_alias.py
quicksave/commands/command_clean.py
quicksave/commands/command_config.py
quicksave/commands/command_delete.py
quicksave/commands/command_export.py
quicksave/commands/command_init.py
quicksave/commands/command_list.py
quicksave/commands/command_lookup.py
quicksave/commands/command_recover.py
quicksave/commands/command_register.py
quicksave/commands/command_revert.py
quicksave/commands/command_save.py
quicksave/commands/command_status.py
quicksave-1.7.0.dist-info/DESCRIPTION.rst
quicksave-1.7.0.dist-info/METADATA
quicksave-1.7.0.dist-info/RECORD
quicksave-1.7.0.dist-info/WHEEL
quicksave-1.7.0.dist-info/entry_points.txt
quicksave-1.7.0.dist-info/metadata.json
quicksave-1.7.0.dist-info/top_level.txt
